{
  "desert":{
    "cameraDelay": 7,
    "playerY": 960,
    "maxJumps": 1,
    "maxDashes": 0,
    "hasGun": false,
    "gun": "",
    "hasSword": false,
    "sword": "",
    "pests":[
      {
        "name": "snake",
        "level": 1,
        "position": "2x29.5"
      },
      {
        "name": "snake",
        "level": 1,
        "position": "18x23.5"
      },
      {
        "name": "spider",
        "level": 1,
        "position": "15x21.5"
      },
      {
        "name": "spider",
        "level": 1,
        "position": "21x21.5"
      }
    ],
    "bosses": [{
      "name": "bigBro",
      "level": 1,
      "position": {"x":400, "y": 232},
      "details": {
        "speed": 200,
        "attackSpeed": 150,
        "stillDamage": 5,
        "attackDamage": 20,
        "decisionTime": 500,
        "jumpVelocity": 200,
        "maxVelocityX": 125,
        "health": 100,
        "hasSword": true,
        "hasGun": true,
        "maxJumps": 2
      }
    }],
    "text": [
      {
        "color": "0x000000",
        "text": "It's too hot",
        "position": {"x": 80, "y": 880},
        "scrollPosition": 710,
        "fadeTime": 75,
        "fadesOut": true
      },
      {
        "color": "0x000000",
        "text": "Press jumpButton to jump",
        "position": {"x": 290, "y": 950},
        "scrollPosition": 900,
        "fadeTime": 100,
        "fadesOut": false
      },
      {
        "color": "0x000000",
        "text": "Press > and jumpButton into a wall to kick off",
        "position": {"x": 192, "y": 765},
        "scrollPosition": 670,
        "fadeTime": 100,
        "fadesOut": false
      },
      {
        "color": "0xFFFFFF",
        "text": "Find your rythm",
        "position": {"x": 280, "y": 600},
        "scrollPosition": 550,
        "fadeTime": 75,
        "fadesOut": true
      },
      {
        "color": "0x000000",
        "text": "Press meleeButton to swing your weapon",
        "position": {"x": 200, "y": 470},
        "scrollPosition": 450,
        "fadeTime": 100,
        "fadesOut": false
      },
      {
        "color": "0xFFFFFF",
        "text": "Here's a gun",
        "position": {"x": 84, "y": 418},
        "scrollPosition": 375,
        "fadeTime": 100,
        "fadesOut": false
      },
      {
        "color": "0xFFFFFF",
        "text": "Did you remember your ammo?  (press shootButton to shoot)",
        "position": {"x": 84, "y": 434},
        "scrollPosition": 325,
        "fadeTime": 100,
        "fadesOut": false
      },
      {
        "color": "0x000000",
        "text": "Big Bro",
        "position": {"x": 350, "y": 200},
        "scrollPosition": 120,
        "fadeTime": 50,
        "fadesOut": true
      }
    ],
    "items": [
      {
        "type": "melee",
        "name": "aluminumBat",
        "position": {"x": 80, "y": 950},
        "size": {"x": 16, "y": 16}
      },
      {
        "type": "ammo",
        "name": "bullets",
        "position": {"x": 234, "y": 966},
        "size": {"x": 16, "y": 16}
      },
      {
        "type": "ammo",
        "name": "bullets",
        "position": {"x": 170, "y": 726},
        "size": {"x": 16, "y": 16}
      },
      {
        "type": "gun",
        "name": "pistol",
        "position": {"x": 24, "y": 406},
        "size": {"x": 16, "y": 16}
      },
      {
        "type": "melee",
        "name": "katana",
        "position": {"x": 362, "y": 358},
        "size": {"x": 16, "y": 16}
      }
    ],
    "nearground": false,
    "bgTileset": false,
    "bgColor": "80e5ff",
    "nextStage": "desertForest"
  },
  "desertForest":{
    "cameraDelay": 6,
    "playerY": 1200,
    "maxJumps": 2,
    "maxDashes": 0,
    "hasGun": false,
    "gun": "",
    "hasSword": false,
    "sword": "",
    "pests":[
      {
        "name": "snake",
        "level": 1,
        "position": "9x52.5"
      },
      {
        "name": "snake",
        "level": 1,
        "position": "20x52.5"
      },
      {
        "name": "snake",
        "level": 1,
        "position": "9x49.5"
      },
      {
        "name": "snake",
        "level": 1,
        "position": "20x49.5"
      },
      {
        "name": "spider",
        "level": 1,
        "position": "14.5x39.5"
      },
      {
        "name": "spider",
        "level": 1,
        "position": "9x22.5"
      },
      {
        "name": "spider",
        "level": 1,
        "position": "20x22.5"
      }
    ],
    "bigBosses": [{
      "name": "forestGuardian",
      "level": 1,
      "position": {"x":240, "y": 100},
      "details": {
        "speed": 180,
        "health": 200,
        "attackSpeed": 180,
        "stillDamage": 25,
        "attackDamage": 35,
        "decisionTime": 400
      }
    }],
    "text": [
      {
        "color": "0xFFFFFF",
        "text": "Which path will you take?",
        "position": {"x": 100, "y": 1120},
        "scrollPosition": 1200,
        "fadeTime": 50,
        "fadesOut": false
      },
      {
        "color": "0x000000",
        "text": "So many snakes...",
        "position": {"x": 180, "y": 750},
        "scrollPosition": 750,
        "fadeTime": 50,
        "fadesOut": false
      },
      {
        "color": "0x000000",
        "text": "...and spiders",
        "position": {"x": 190, "y": 560},
        "scrollPosition": 500,
        "fadeTime": 50,
        "fadesOut": true
      },
      {
        "color": "0x000000",
        "text": "Forest Guardian",
        "position": {"x": 180, "y": 190},
        "scrollPosition": 100,
        "fadeTime": 50,
        "fadesOut": true
      }
    ],
    "items": [
      {
        "type": "melee",
        "name": "aluminumBat",
        "position": {"x": 56, "y": 966},
        "size": {"x": 16, "y": 16}
      },
      {
        "type": "melee",
        "name": "katana",
        "position": {"x": 456, "y": 998},
        "size": {"x": 16, "y": 16}
      },
      {
        "type": "ammo",
        "name": "bullets",
        "position": {"x": 362, "y": 966},
        "size": {"x": 16, "y": 16}
      },
      {
        "type": "gun",
        "name": "pistol",
        "position": {"x": 242, "y": 790},
        "size": {"x": 16, "y": 16}
      },
      {
        "type": "ammo",
        "name": "bullets",
        "position": {"x": 424, "y": 1142},
        "size": {"x": 16, "y": 16}
      },
      {
        "type": "ammo",
        "name": "bullets",
        "position": {"x": 24, "y": 838},
        "size": {"x": 16, "y": 16}
      },
      {
        "type": "ammo",
        "name": "bullets",
        "position": {"x": 458, "y": 838},
        "size": {"x": 16, "y": 16}
      },
      {
        "type": "ammo",
        "name": "bullets",
        "position": {"x": 24, "y": 726},
        "size": {"x": 16, "y": 16}
      },
      {
        "type": "ammo",
        "name": "bullets",
        "position": {"x": 458, "y": 726},
        "size": {"x": 16, "y": 16}
      },
      {
        "type": "ammo",
        "name": "bullets",
        "position": {"x": 24, "y": 502},
        "size": {"x": 16, "y": 16}
      },
      {
        "type": "ammo",
        "name": "bullets",
        "position": {"x": 458, "y": 502},
        "size": {"x": 16, "y": 16}
      }
    ],
    "nearground": false,
    "bgTileset": false,
    "bgColor": "80fcf4",
    "nextStage": "forest"
  },
  "forest":{
    "cameraDelay": 5,
    "playerY": 1440,
    "maxJumps": 2,
    "maxDashes": 1,
    "hasGun": false,
    "gun": "",
    "hasSword": false,
    "sword": "",
    "pests":[
      {
        "name": "spider",
        "level": 1,
        "position": "9x71.5"
      },
      {
        "name": "spider",
        "level": 1,
        "position": "21x72.5"
      },
      {
        "name": "snake",
        "level": 1,
        "position": "7x53.5"
      },
      {
        "name": "snake",
        "level": 1,
        "position": "11x51.5"
      },
      {
        "name": "snake",
        "level": 1,
        "position": "5x30.5"
      },
      {
        "name": "snake",
        "level": 1,
        "position": "24x30.5"
      },
      {
        "name": "snake",
        "level": 1,
        "position": "9x26.5"
      },
      {
        "name": "snake",
        "level": 1,
        "position": "20x26.5"
      }
    ],
    "bosses": [{
      "name": "littleBro",
      "level": 1,
      "position": {"x":40, "y": 232},
      "details": {
        "speed": 200,
        "attackSpeed": 150,
        "stillDamage": 5,
        "attackDamage": 20,
        "decisionTime": 500,
        "jumpVelocity": 200,
        "maxVelocityX": 125,
        "health": 100,
        "hasSword": true,
        "hasGun": true,
        "maxJumps": 2
      }
    }, {
      "name": "littleBro",
      "level": 1,
      "position": {"x":120, "y": 232},
      "details": {
        "speed": 200,
        "attackSpeed": 150,
        "stillDamage": 5,
        "attackDamage": 20,
        "decisionTime": 500,
        "jumpVelocity": 200,
        "maxVelocityX": 125,
        "health": 100,
        "hasSword": true,
        "hasGun": true,
        "maxJumps": 2
      }
    }],
    "text": [
      {
        "color": "0x000000",
        "text": "Use dashButton to dash.  Good luck.",
        "position": {"x": 240, "y": 1420},
        "scrollPosition": 1440,
        "fadeTime": 100,
        "fadesOut": false
      },
      {
        "color": "0x000000",
        "text": "jump + jump + dash or jump + dash + jump?",
        "position": {"x": 150, "y": 1140},
        "scrollPosition": 1100,
        "fadeTime": 100,
        "fadesOut": false
      },
      {
        "color": "0x000000",
        "text": "Little Bros",
        "position": {"x": 48, "y": 200},
        "scrollPosition": 50,
        "fadeTime": 100,
        "fadesOut": true
      }
    ],
    "items": [
      {
        "type": "melee",
        "name": "aluminumBat",
        "position": {"x": 456, "y": 1254},
        "size": {"x": 16, "y": 16}
      },
      {
        "type": "ammo",
        "name": "bullets",
        "position": {"x": 280, "y": 822},
        "size": {"x": 16, "y": 16}
      },
      {
        "type": "ammo",
        "name": "bullets",
        "position": {"x": 344, "y": 838},
        "size": {"x": 16, "y": 16}
      },
      {
        "type": "ammo",
        "name": "bullets",
        "position": {"x": 426, "y": 870},
        "size": {"x": 16, "y": 16}
      },
      {
        "type": "melee",
        "name": "katana",
        "position": {"x": 216, "y": 310},
        "size": {"x": 16, "y": 16}
      },
      {
        "type": "gun",
        "name": "pistol",
        "position": {"x": 264, "y": 310},
        "size": {"x": 16, "y": 16}
      },
      {
        "type": "ammo",
        "name": "bullets",
        "position": {"x": 296, "y": 310},
        "size": {"x": 16, "y": 16}
      },
      {
        "type": "ammo",
        "name": "bullets",
        "position": {"x": 328, "y": 310},
        "size": {"x": 16, "y": 16}
      }
    ],
    "nearground": false,
    "bgTileset": false,
    "bgColor": "80ffeb",
    "nextStage": "end"
  }
}